pluaris_sdk/__init__.py
pluaris_sdk/log.py
pluaris_sdk/verification.py
pluaris_sdk-0.0.8.dist-info/METADATA
pluaris_sdk-0.0.8.dist-info/WHEEL
pluaris_sdk-0.0.8.dist-info/top_level.txt
pluaris_sdk-0.0.8.dist-info/RECORD
