Metadata-Version: 2.1
Name: pluaris-sdk
Version: 0.0.8
Summary: Create a DAPP for your organisation and Manage all your Organisational Activities.
Home-page: UNKNOWN
Author: Chethan Pasupuleti
Author-email: <chethanpss24@gmail.com>
License: UNKNOWN
Keywords: python,pluaris,algorand,sdk,smart contract
Platform: UNKNOWN
Classifier: Development Status :: 1 - Planning
Classifier: Intended Audience :: Developers
Classifier: Programming Language :: Python :: 3
Classifier: Operating System :: Unix
Classifier: Operating System :: MacOS :: MacOS X
Classifier: Operating System :: Microsoft :: Windows
Requires-Dist: requests
